odoo/addons/currency_rate_update_cmc/README.rst
odoo/addons/currency_rate_update_cmc/__init__.py
odoo/addons/currency_rate_update_cmc/__manifest__.py
odoo/addons/currency_rate_update_cmc/i18n/currency_rate_update_cmc.pot
odoo/addons/currency_rate_update_cmc/services/__init__.py
odoo/addons/currency_rate_update_cmc/services/update_service_CMC.py
odoo/addons/currency_rate_update_cmc/static/description/icon.png
odoo11_addon_currency_rate_update_cmc-11.0.1.0.0.99.dev3.dist-info/DESCRIPTION.rst
odoo11_addon_currency_rate_update_cmc-11.0.1.0.0.99.dev3.dist-info/METADATA
odoo11_addon_currency_rate_update_cmc-11.0.1.0.0.99.dev3.dist-info/RECORD
odoo11_addon_currency_rate_update_cmc-11.0.1.0.0.99.dev3.dist-info/WHEEL
odoo11_addon_currency_rate_update_cmc-11.0.1.0.0.99.dev3.dist-info/metadata.json
odoo11_addon_currency_rate_update_cmc-11.0.1.0.0.99.dev3.dist-info/top_level.txt
